tripy.py
tripy-0.0.3.dist-info/DESCRIPTION.rst
tripy-0.0.3.dist-info/METADATA
tripy-0.0.3.dist-info/RECORD
tripy-0.0.3.dist-info/WHEEL
tripy-0.0.3.dist-info/metadata.json
tripy-0.0.3.dist-info/top_level.txt
