Metadata-Version: 2.0
Name: tripy
Version: 0.0.3
Summary: Simple polygon triangulation
Home-page: https://github.com/linuxlewis/tripy
Author: Sam Bolgert
Author-email: sbolgert@gmail.com
License: MIT
Platform: UNKNOWN
Classifier: Programming Language :: Python :: 2.7
Classifier: Programming Language :: Python :: 3
Classifier: Programming Language :: Python :: 3.6
